LICENSE.txt
README.md
setup.cfg
setup.py
prometheus_pgbouncer_exporter/__init__.py
prometheus_pgbouncer_exporter/cli.py
prometheus_pgbouncer_exporter/collector.py
prometheus_pgbouncer_exporter/config.py
prometheus_pgbouncer_exporter.egg-info/PKG-INFO
prometheus_pgbouncer_exporter.egg-info/SOURCES.txt
prometheus_pgbouncer_exporter.egg-info/dependency_links.txt
prometheus_pgbouncer_exporter.egg-info/entry_points.txt
prometheus_pgbouncer_exporter.egg-info/requires.txt
prometheus_pgbouncer_exporter.egg-info/top_level.txt