Metadata-Version: 2.1
Name: prometheus-pgbouncer-exporter
Version: 2.1.2
Summary: Prometheus exporter for PgBouncer
Home-page: https://github.com/spreaker/prometheus-pgbouncer-exporter
Download-URL: https://github.com/spreaker/prometheus-pgbouncer-exporter/archive/2.1.1.tar.gz
Author: Spreaker Developers
Author-email: dev@spreaker.com
License: UNKNOWN
Keywords: prometheus,pgbouncer
Platform: UNKNOWN
Requires-Python:  >= 3
License-File: LICENSE.txt
